modulitiz_micro/ModuloSeriale.py
modulitiz_micro/ModuloTarghe.py
modulitiz_micro/database/AbstractDatabaseService.py
modulitiz_micro/database/AbstractSql.py
modulitiz_micro/database/ModuloSqlOracle.py
modulitiz_micro/database/ModuloSqlServer.py
modulitiz_micro/database/exceptions/ExceptionDbNoData.py
modulitiz_micro/database/mysql/AbstractBasicMysql.py
modulitiz_micro/database/mysql/ModuloMysql.py
modulitiz_micro/database/mysql/MysqlCommonConverter.py
modulitiz_micro/database/mysql/exceptions/ExceptionMysqlOffline.py
modulitiz_micro/database/sqlite/AbstractBasicSQLite.py
modulitiz_micro/database/sqlite/ModuloSQLite.py
modulitiz_micro/exceptions/ExceptionCtrlC.py
modulitiz_micro/exceptions/ExceptionScheduler.py
modulitiz_micro/exceptions/http/ExceptionHttp.py
modulitiz_micro/exceptions/http/ExceptionHttp404.py
modulitiz_micro/exceptions/http/ExceptionHttpGeneric.py
modulitiz_micro/exceptions/http/ExceptionHttpRetriesExceeded.py
modulitiz_micro/files/cache/DatabaseCache.py
modulitiz_micro/files/cache/decorators/cacheRam.py
modulitiz_micro/files/git/ModuloGit.py
modulitiz_micro/files/git/decorators/catchAndRaiseGitExceptions.py
modulitiz_micro/files/git/exceptions/ExceptionGit.py
modulitiz_micro/gestionedom/GestioneDom.py
modulitiz_micro/iot/ModuleIotDevice.py
modulitiz_micro/iot/beans/IotDeviceBean.py
modulitiz_micro/iot/enums/IotOSEnum.py
modulitiz_micro/iot/espurna/ModuleEspurna.py
modulitiz_micro/keylogger/ExceptionKeyLogger.py
modulitiz_micro/keylogger/ModuloKeylogger.py
modulitiz_micro/rete/ModuleAndroidTVRemote.py
modulitiz_micro/rete/ModuloNetworking.py
modulitiz_micro/rete/ModuloOpenVpn.py
modulitiz_micro/rete/email/EmailBean.py
modulitiz_micro/rete/email/ModuloEmail.py
modulitiz_micro/rete/http/ModuloHttp.py
modulitiz_micro/rete/http/ModuloHttpConnectionSafe.py
modulitiz_micro/rete/http/ModuloHttpUtils.py
modulitiz_micro/rete/http/beans/HttpResponseBean.py
modulitiz_micro/rete/http/decorators/catchAndRaiseHttpExceptions.py
modulitiz_micro-2.53.0.dist-info/licenses/LICENSE
modulitiz_micro-2.53.0.dist-info/METADATA
modulitiz_micro-2.53.0.dist-info/WHEEL
modulitiz_micro-2.53.0.dist-info/top_level.txt
modulitiz_micro-2.53.0.dist-info/RECORD
