Metadata-Version: 2.4
Name: modulitiz_micro
Version: 2.53.0
Summary: Raccolta dei miei moduli - versione micro
Author-email: tiz <sderfo1234@altervista.org>
Classifier: Programming Language :: Python :: 3
Classifier: Operating System :: OS Independent
Requires-Python: >=3.11
License-File: LICENSE
Requires-Dist: modulitiz-nano>=0
Requires-Dist: androidtvremote2==0.3.0
Requires-Dist: beautifulsoup4==4.14.3
Requires-Dist: brotli==1.2.0
Requires-Dist: cachetools==6.2.4
Requires-Dist: cryptography==45.0.6
Requires-Dist: GitPython==3.1.46
Requires-Dist: mysql_connector_python==9.5.0
Requires-Dist: pynput==1.8.1
Requires-Dist: pyOpenSSL==25.1.0
Requires-Dist: pypyodbc==1.3.6
Requires-Dist: pyserial==3.5
Requires-Dist: requests==2.32.5
Requires-Dist: scapy==2.7.0
Requires-Dist: schedule==1.2.2
Requires-Dist: telethon==1.42.0
Dynamic: license-file
